README.md
setup.cfg
setup.py
we_are_venom/__init__.py
we_are_venom/commit.py
we_are_venom/common_types.py
we_are_venom/venom.py
we_are_venom.egg-info/PKG-INFO
we_are_venom.egg-info/SOURCES.txt
we_are_venom.egg-info/dependency_links.txt
we_are_venom.egg-info/entry_points.txt
we_are_venom.egg-info/not-zip-safe
we_are_venom.egg-info/requires.txt
we_are_venom.egg-info/top_level.txt
we_are_venom/utils/__init__.py
we_are_venom/utils/accumulation.py
we_are_venom/utils/config.py
we_are_venom/utils/files.py
we_are_venom/utils/git.py
we_are_venom/utils/lists.py
we_are_venom/utils/output.py
we_are_venom/utils/review.py