Metadata-Version: 2.1
Name: we-are-venom
Version: 0.0.2
Summary: Checks which modules developer contributed using git history.
Home-page: https://github.com/best-doctor/we_are_venom
Author: Ilya Lebedev
Author-email: melevir@gmail.com
License: MIT
Keywords: plugins git statistics
Platform: UNKNOWN
Classifier: Environment :: Console
Classifier: Operating System :: OS Independent
Classifier: Topic :: Software Development :: Libraries :: Python Modules
Classifier: Topic :: Software Development :: Quality Assurance
Classifier: Programming Language :: Python
Classifier: Programming Language :: Python :: 3.7
Classifier: Programming Language :: Python :: 3.8
Classifier: Programming Language :: Python :: 3.9
